{
  "Apple": {
    "iPhone (2G)": { "Chip": "Samsung APL0098", "Screen": "3.5-inch TFT", "Camera": "2 MP", "Battery": "1400 mAh", "Released": "2007" },
    "iPhone 3G": { "Chip": "Samsung S5L8900", "Screen": "3.5-inch TFT", "Camera": "2 MP", "Battery": "1150 mAh", "Released": "2008" },
    "iPhone 3GS": { "Chip": "Samsung S5PC100", "Screen": "3.5-inch TFT", "Camera": "3.15 MP", "Battery": "1219 mAh", "Released": "2009" },
    "iPhone 4": { "Chip": "Apple A4", "Screen": "3.5-inch Retina IPS", "Camera": "5 MP", "Battery": "1420 mAh", "Released": "2010" },
    "iPhone 4S": { "Chip": "Apple A5", "Screen": "3.5-inch Retina IPS", "Camera": "8 MP", "Battery": "1432 mAh", "Released": "2011" },
    "iPhone 5": { "Chip": "Apple A6", "Screen": "4.0-inch Retina IPS", "Camera": "8 MP", "Battery": "1440 mAh", "Released": "2012" },
    "iPhone 5s": { "Chip": "Apple A7 (64-bit)", "Screen": "4.0-inch Retina IPS", "Camera": "8 MP", "Battery": "1560 mAh", "Released": "2013" },
    "iPhone 5c": { "Chip": "Apple A6", "Screen": "4.0-inch Retina IPS", "Camera": "8 MP", "Battery": "1510 mAh", "Released": "2013" },
    "iPhone 6": { "Chip": "Apple A8", "Screen": "4.7-inch IPS", "Camera": "8 MP", "Battery": "1810 mAh", "Released": "2014" },
    "iPhone 6 Plus": { "Chip": "Apple A8", "Screen": "5.5-inch IPS", "Camera": "8 MP (OIS)", "Battery": "2915 mAh", "Released": "2014" },
    "iPhone 6s": { "Chip": "Apple A9", "Screen": "4.7-inch IPS", "Camera": "12 MP", "Battery": "1715 mAh", "Released": "2015" },
    "iPhone SE (1st Gen)": { "Chip": "Apple A9", "Screen": "4.0-inch IPS", "Camera": "12 MP", "Battery": "1624 mAh", "Released": "2016" },
    "iPhone 7": { "Chip": "Apple A10 Fusion", "Screen": "4.7-inch IPS", "Camera": "12 MP", "Battery": "1960 mAh", "Released": "2016" },
    "iPhone 7 Plus": { "Chip": "Apple A10 Fusion", "Screen": "5.5-inch IPS", "Camera": "Dual 12 MP", "Battery": "2900 mAh", "Released": "2016" },
    "iPhone 8": { "Chip": "Apple A11 Bionic", "Screen": "4.7-inch IPS", "Camera": "12 MP", "Battery": "1821 mAh", "Released": "2017" },
    "iPhone 8 Plus": { "Chip": "Apple A11 Bionic", "Screen": "5.5-inch IPS", "Camera": "Dual 12 MP", "Battery": "2691 mAh", "Released": "2017" },
    "iPhone X": { "Chip": "Apple A11 Bionic", "Screen": "5.8-inch Super Retina OLED", "Camera": "Dual 12 MP", "Battery": "2716 mAh", "Released": "2017" },
    "iPhone XR": { "Chip": "Apple A12 Bionic", "Screen": "6.1-inch Liquid Retina IPS", "Camera": "12 MP", "Battery": "2942 mAh", "Released": "2018" },
    "iPhone XS Max": { "Chip": "Apple A12 Bionic", "Screen": "6.5-inch Super Retina OLED", "Camera": "Dual 12 MP", "Battery": "3174 mAh", "Released": "2018" },
    "iPhone 11": { "Chip": "Apple A13 Bionic", "Screen": "6.1-inch Liquid Retina IPS", "Camera": "Dual 12 MP", "Battery": "3110 mAh", "Released": "2019" },
    "iPhone 11 Pro": { "Chip": "Apple A13 Bionic", "Screen": "5.8-inch Super Retina XDR OLED", "Camera": "Triple 12 MP", "Battery": "3046 mAh", "Released": "2019" },
    "iPhone 11 Pro Max": { "Chip": "Apple A13 Bionic", "Screen": "6.5-inch Super Retina XDR OLED", "Camera": "Triple 12 MP", "Battery": "3969 mAh", "Released": "2019" },
    "iPhone SE (2nd Gen)": { "Chip": "Apple A13 Bionic", "Screen": "4.7-inch Retina IPS", "Camera": "12 MP", "Battery": "1821 mAh", "Released": "2020" },
    "iPhone 12": { "Chip": "Apple A14 Bionic", "Screen": "6.1-inch Super Retina XDR OLED", "Camera": "Dual 12 MP", "Battery": "2815 mAh", "Released": "2020" },
    "iPhone 12 Pro": { "Chip": "Apple A14 Bionic", "Screen": "6.1-inch Super Retina XDR OLED", "Camera": "Triple 12 MP + LiDAR", "Battery": "2815 mAh", "Released": "2020" },
    "iPhone 12 Pro Max": { "Chip": "Apple A14 Bionic", "Screen": "6.7-inch Super Retina XDR OLED", "Camera": "Triple 12 MP + LiDAR", "Battery": "3687 mAh", "Released": "2020" },
    "iPhone 13": { "Chip": "Apple A15 Bionic", "Screen": "6.1-inch Super Retina XDR OLED", "Camera": "Dual 12 MP", "Battery": "3227 mAh", "Released": "2021" },
    "iPhone 13 Pro": { "Chip": "Apple A15 Bionic", "Screen": "6.1-inch Super Retina OLED (120Hz)", "Camera": "Triple 12 MP + LiDAR", "Battery": "3095 mAh", "Released": "2021" },
    "iPhone 13 Pro Max": { "Chip": "Apple A15 Bionic", "Screen": "6.7-inch Super Retina XDR OLED (120Hz)", "Camera": "Triple 12 MP + LiDAR", "Battery": "4352 mAh", "Released": "2021" },
    "iPhone SE (3rd Gen)": { "Chip": "Apple A15 Bionic", "Screen": "4.7-inch Retina IPS", "Camera": "12 MP", "Battery": "2018 mAh", "Released": "2022" },
    "iPhone 14": { "Chip": "Apple A15 Bionic", "Screen": "6.1-inch Super Retina XDR OLED", "Camera": "Dual 12 MP", "Battery": "3279 mAh", "Released": "2022" },
    "iPhone 14 Pro": { "Chip": "Apple A16 Bionic", "Screen": "6.1-inch LTPO Super Retina OLED", "Camera": "Triple 48 MP + 12 MP + 12 MP", "Battery": "3200 mAh", "Released": "2022" },
    "iPhone 14 Pro Max": { "Chip": "Apple A16 Bionic", "Screen": "6.7-inch LTPO Super Retina OLED", "Camera": "Triple 48 MP + 12 MP + 12 MP", "Battery": "4323 mAh", "Released": "2022" },
    "iPhone 15": { "Chip": "Apple A16 Bionic", "Screen": "6.1-inch Super Retina XDR OLED", "Camera": "Dual 48 MP + 12 MP", "Battery": "3349 mAh", "Released": "2023" },
    "iPhone 15 Pro": { "Chip": "Apple A17 Pro", "Screen": "6.1-inch LTPO Super Retina OLED", "Camera": "Triple 48 MP + 12 MP + 12 MP", "Battery": "3274 mAh", "Released": "2023" },
    "iPhone 15 Pro Max": { "Chip": "Apple A17 Pro", "Screen": "6.7-inch LTPO Super Retina OLED", "Camera": "Triple 48 MP + 12 MP + 12 MP", "Battery": "4441 mAh", "Released": "2023" },
    "iPhone 16": { "Chip": "Apple A18", "Screen": "6.1-inch Super Retina XDR OLED", "Camera": "Dual 48 MP + 12 MP", "Battery": "3561 mAh", "Released": "2024" },
    "iPhone 16 Pro": { "Chip": "Apple A18 Pro", "Screen": "6.3-inch LTPO Super Retina OLED", "Camera": "Triple 48 MP + 48 MP + 12 MP", "Battery": "3582 mAh", "Released": "2024" },
    "iPhone 16 Pro Max": { "Chip": "Apple A18 Pro", "Screen": "6.9-inch LTPO Super Retina OLED", "Camera": "Triple 48 MP + 48 MP + 12 MP", "Battery": "4685 mAh", "Released": "2024" },
    "iPhone 17 Pro Max": { "Chip": "Apple A19 Pro", "Screen": "6.9-inch LTPO Super Retina OLED (120Hz)", "Camera": "Triple 48 MP + 48 MP + 48 MP", "Battery": "4823 mAh", "Released": "2025" }
  },
  "Samsung": {
    "SGH-A100": { "Chip": "Proprietary", "Screen": "Mono Graphic", "Camera": "None", "Battery": "900 mAh", "Released": "2000" },
    "SPH-i300": { "Chip": "Motorola Dragonball EZ", "Screen": "2.4-inch Color Resistive", "Camera": "None", "Battery": "1000 mAh", "Released": "2001" },
    "SGH-T100": { "Chip": "Proprietary", "Screen": "2.1-inch CSTN Color", "Camera": "None", "Battery": "720 mAh", "Released": "2002" },
    "SGH-E700": { "Chip": "Proprietary", "Screen": "1.8-inch TFT Color", "Camera": "VGA (0.3 MP)", "Battery": "780 mAh", "Released": "2003" },
    "SGH-D500": { "Chip": "Proprietary", "Screen": "1.9-inch TFT", "Camera": "1.3 MP", "Battery": "800 mAh", "Released": "2004" },
    "SGH-D600": { "Chip": "Proprietary", "Screen": "2.0-inch TFT", "Camera": "2.0 MP", "Battery": "850 mAh", "Released": "2005" },
    "SGH-i607 BlackJack": { "Chip": "ARM9 220 MHz", "Screen": "2.25-inch TFT", "Camera": "1.3 MP", "Battery": "1200 mAh", "Released": "2006" },
    "SGH-U900 Soul": { "Chip": "Proprietary", "Screen": "2.2-inch TFT", "Camera": "5.0 MP", "Battery": "880 mAh", "Released": "2008" },
    "SGH-i900 Omnia": { "Chip": "Marvell PXA312", "Screen": "3.2-inch TFT Touch", "Camera": "5.0 MP", "Battery": "1440 mAh", "Released": "2008" },
    "GT-i7500 Galaxy": { "Chip": "Qualcomm MSM7200A", "Screen": "3.2-inch AMOLED Touch", "Camera": "5.0 MP", "Battery": "1500 mAh", "Released": "2009" },
    "Galaxy S": { "Chip": "Hummingbird 1.0 GHz", "Screen": "4.0-inch Super AMOLED", "Camera": "5.0 MP", "Battery": "1500 mAh", "Released": "2010" },
    "Galaxy Note (GT-N7000)": { "Chip": "Exynos 4 Dual", "Screen": "5.3-inch Super AMOLED", "Camera": "8.0 MP", "Battery": "2500 mAh", "Released": "2011" },
    "Galaxy S II": { "Chip": "Exynos 4210 Dual", "Screen": "4.3-inch Super AMOLED Plus", "Camera": "8.0 MP", "Battery": "1650 mAh", "Released": "2011" },
    "Galaxy S III": { "Chip": "Exynos 4412 Quad", "Screen": "4.8-inch Super AMOLED", "Camera": "8.0 MP", "Battery": "2100 mAh", "Released": "2012" },
    "Galaxy S4": { "Chip": "Exynos 5 Octa 5410", "Screen": "5.0-inch Super AMOLED", "Camera": "13.0 MP", "Battery": "2600 mAh", "Released": "2013" },
    "Galaxy S5": { "Chip": "Snapdragon 801", "Screen": "5.1-inch Super AMOLED", "Camera": "16.0 MP", "Battery": "2800 mAh", "Released": "2014" },
    "Galaxy S6 Edge": { "Chip": "Exynos 7420 Octa", "Screen": "5.1-inch Curved Super AMOLED", "Camera": "16.0 MP (OIS)", "Battery": "2600 mAh", "Released": "2015" },
    "Galaxy S7 Edge": { "Chip": "Snapdragon 820 / Exynos 8890", "Screen": "5.5-inch Curved Super AMOLED", "Camera": "12.0 MP Dual Pixel", "Battery": "3600 mAh", "Released": "2016" },
    "Galaxy S8": { "Chip": "Snapdragon 835 / Exynos 8895", "Screen": "5.8-inch Infinity Super AMOLED", "Camera": "12.0 MP Dual Pixel", "Battery": "3000 mAh", "Released": "2017" },
    "Galaxy S9+": { "Chip": "Snapdragon 845 / Exynos 9810", "Screen": "6.2-inch Super AMOLED", "Camera": "Dual 12 MP", "Battery": "3500 mAh", "Released": "2018" },
    "Galaxy S10": { "Chip": "Snapdragon 855 / Exynos 9820", "Screen": "6.1-inch Dynamic AMOLED", "Camera": "Triple 12 MP + 12 MP + 16 MP", "Battery": "3400 mAh", "Released": "2019" },
    "Galaxy S10+": { "Chip": "Snapdragon 855 / Exynos 9820", "Screen": "6.4-inch Dynamic AMOLED", "Camera": "Triple 12 MP + 12 MP + 16 MP", "Battery": "4100 mAh", "Released": "2019" },
    "Galaxy Fold": { "Chip": "Snapdragon 855", "Screen": "7.3-inch Foldable Dynamic AMOLED", "Camera": "Triple 12 MP + 12 MP + 16 MP", "Battery": "4380 mAh", "Released": "2019" },
    "Galaxy S20": { "Chip": "Snapdragon 865 / Exynos 990", "Screen": "6.2-inch Dynamic AMOLED 2X", "Camera": "Triple 12 MP + 64 MP + 12 MP", "Battery": "4000 mAh", "Released": "2020" },
    "Galaxy S20 Ultra": { "Chip": "Snapdragon 865 / Exynos 990", "Screen": "6.9-inch Dynamic AMOLED (120Hz)", "Camera": "Quad 108 MP + 48 MP + 12 MP + TOF", "Battery": "5000 mAh", "Released": "2020" },
    "Galaxy S21": { "Chip": "Snapdragon 888 / Exynos 2100", "Screen": "6.2-inch Dynamic AMOLED 2X", "Camera": "Triple 12 MP + 64 MP + 12 MP", "Battery": "4000 mAh", "Released": "2021" },
    "Galaxy S21 Ultra": { "Chip": "Snapdragon 888 / Exynos 2100", "Screen": "6.8-inch Dynamic AMOLED 2X", "Camera": "Quad 108 MP + 10 MP + 10 MP + 12 MP", "Battery": "5000 mAh", "Released": "2021" },
    "Galaxy S22": { "Chip": "Snapdragon 8 Gen 1 / Exynos 2200", "Screen": "6.1-inch Dynamic AMOLED 2X", "Camera": "Triple 50 MP + 10 MP + 12 MP", "Battery": "3700 mAh", "Released": "2022" },
    "Galaxy S22 Ultra": { "Chip": "Snapdragon 8 Gen 1 / Exynos 2200", "Screen": "6.8-inch Dynamic AMOLED 2X", "Camera": "Quad 108 MP + 10 MP + 10 MP + 12 MP", "Battery": "5000 mAh", "Released": "2022" },
    "Galaxy S23": { "Chip": "Snapdragon 8 Gen 2 for Galaxy", "Screen": "6.1-inch Dynamic AMOLED 2X", "Camera": "Triple 50 MP + 10 MP + 12 MP", "Battery": "3900 mAh", "Released": "2023" },
    "Galaxy S23 Ultra": { "Chip": "Snapdragon 8 Gen 2 for Galaxy", "Screen": "6.8-inch Dynamic AMOLED 2X", "Camera": "Quad 200 MP + 10 MP + 10 MP + 12 MP", "Battery": "5000 mAh", "Released": "2023" },
    "Galaxy S24": { "Chip": "Snapdragon 8 Gen 3 / Exynos 2400", "Screen": "6.2-inch Dynamic AMOLED 2X", "Camera": "Triple 50 MP + 10 MP + 12 MP", "Battery": "4000 mAh", "Released": "2024" },
    "Galaxy S24 Ultra": { "Chip": "Snapdragon 8 Gen 3 for Galaxy", "Screen": "6.8-inch Dynamic AMOLED 2X", "Camera": "Quad 200 MP + 50 MP + 10 MP + 12 MP", "Battery": "5000 mAh", "Released": "2024" },
    "Galaxy S25": { "Chip": "Snapdragon 8 Elite", "Screen": "6.2-inch Dynamic AMOLED 2X", "Camera": "Triple 50 MP + 10 MP + 12 MP", "Battery": "4000 mAh", "Released": "2025" },
    "Galaxy S25 Ultra": { "Chip": "Snapdragon 8 Elite", "Screen": "6.8-inch Dynamic AMOLED 2X", "Camera": "Quad 200 MP + 50 MP + 50 MP + 12 MP", "Battery": "5000 mAh", "Released": "2025" },
    "Galaxy S26 Ultra": { "Chip": "Snapdragon 8 Elite Gen 5", "Screen": "6.9-inch Dynamic AMOLED 2X", "Camera": "Quad 200 MP + 50 MP + 50 MP + 12 MP", "Battery": "5000 mAh", "Released": "2026" }
  },
  "Xiaomi": {
    "Mi 1": { "Chip": "Snapdragon S3", "Screen": "4.0-inch TFT", "Camera": "8 MP", "Battery": "1930 mAh", "Released": "2011" },
    "Mi 2": { "Chip": "Snapdragon S4 Pro", "Screen": "4.3-inch IPS LCD", "Camera": "8 MP", "Battery": "2000 mAh", "Released": "2012" },
    "Mi 3": { "Chip": "Snapdragon 800", "Screen": "5.0-inch IPS LCD", "Camera": "13 MP", "Battery": "3050 mAh", "Released": "2013" },
    "Redmi 1": { "Chip": "MediaTek MT6589T", "Screen": "4.7-inch IPS LCD", "Camera": "8 MP", "Battery": "2000 mAh", "Released": "2013" },
    "Mi 4": { "Chip": "Snapdragon 801", "Screen": "5.0-inch IPS LCD", "Camera": "13 MP", "Battery": "3080 mAh", "Released": "2014" },
    "Mi 5": { "Chip": "Snapdragon 820", "Screen": "5.15-inch IPS LCD", "Camera": "16 MP (4-axis OIS)", "Battery": "3000 mAh", "Released": "2016" },
    "Mi Mix": { "Chip": "Snapdragon 821", "Screen": "6.4-inch IPS LCD Borderless", "Camera": "16 MP", "Battery": "4400 mAh", "Released": "2016" },
    "Mi 6": { "Chip": "Snapdragon 835", "Screen": "5.15-inch IPS LCD", "Camera": "Dual 12 MP", "Battery": "3350 mAh", "Released": "2017" },
    "Mi 8": { "Chip": "Snapdragon 845", "Screen": "6.21-inch Super AMOLED", "Camera": "Dual 12 MP", "Battery": "3400 mAh", "Released": "2018" },
    "Pocophone F1": { "Chip": "Snapdragon 845", "Screen": "6.18-inch IPS LCD", "Camera": "Dual 12 MP + 5 MP", "Battery": "4000 mAh", "Released": "2018" },
    "Mi 9": { "Chip": "Snapdragon 855", "Screen": "6.39-inch Super AMOLED", "Camera": "Triple 48 MP + 12 MP + 16 MP", "Battery": "3300 mAh", "Released": "2019" },
    "Mi Note 10": { "Chip": "Snapdragon 730G", "Screen": "6.47-inch AMOLED", "Camera": "Penta 108 MP + 12 MP + 20 MP + 8 MP + 2 MP", "Battery": "5260 mAh", "Released": "2019" },
    "Mi 10": { "Chip": "Snapdragon 865", "Screen": "6.67-inch Super AMOLED", "Camera": "Quad 108 MP + 13 MP + 2 MP + 2 MP", "Battery": "4780 mAh", "Released": "2020" },
    "Mi 10 Pro": { "Chip": "Snapdragon 865", "Screen": "6.67-inch Super AMOLED (90Hz)", "Camera": "Quad 108 MP + 12 MP + 8 MP + 20 MP", "Battery": "4500 mAh", "Released": "2020" },
    "Mi 11": { "Chip": "Snapdragon 888", "Screen": "6.81-inch AMOLED", "Camera": "Triple 108 MP + 13 MP + 5 MP", "Battery": "4600 mAh", "Released": "2021" },
    "Mi 11 Pro": { "Chip": "Snapdragon 888", "Screen": "6.81-inch AMOLED", "Camera": "Triple 50 MP + 8 MP + 13 MP", "Battery": "5000 mAh", "Released": "2021" },
    "Mi 11 Ultra": { "Chip": "Snapdragon 888", "Screen": "6.81-inch AMOLED (120Hz)", "Camera": "Triple 50 MP + 48 MP + 48 MP", "Battery": "5000 mAh", "Released": "2021" },
    "Xiaomi 12": { "Chip": "Snapdragon 8 Gen 1", "Screen": "6.28-inch AMOLED", "Camera": "Triple 50 MP + 13 MP + 5 MP", "Battery": "4500 mAh", "Released": "2021" },
    "Xiaomi 12 Pro": { "Chip": "Snapdragon 8 Gen 1", "Screen": "6.73-inch LTPO AMOLED", "Camera": "Triple 50 MP + 50 MP + 50 MP", "Battery": "4600 mAh", "Released": "2021" },
    "Xiaomi 12S": { "Chip": "Snapdragon 8+ Gen 1", "Screen": "6.28-inch AMOLED", "Camera": "Triple 50 MP + 13 MP + 5 MP", "Battery": "4500 mAh", "Released": "2022" },
    "Xiaomi 12S Pro": { "Chip": "Snapdragon 8+ Gen 1", "Screen": "6.73-inch LTPO2 AMOLED", "Camera": "Triple 50 MP + 50 MP + 50 MP", "Battery": "4600 mAh", "Released": "2022" },
    "Xiaomi 12S Ultra": { "Chip": "Snapdragon 8+ Gen 1", "Screen": "6.73-inch LTPO2 AMOLED", "Camera": "Triple 50.3 MP + 48 MP + 48 MP", "Battery": "4860 mAh", "Released": "2022" },
    "Xiaomi 13": { "Chip": "Snapdragon 8 Gen 2", "Screen": "6.36-inch AMOLED", "Camera": "Triple 50 MP + 10 MP + 12 MP", "Battery": "4500 mAh", "Released": "2022" },
    "Xiaomi 13 Pro": { "Chip": "Snapdragon 8 Gen 2", "Screen": "6.73-inch LTPO AMOLED", "Camera": "Triple 50.3 MP + 50 MP + 50 MP", "Battery": "4820 mAh", "Released": "2022" },
    "Xiaomi 13 Ultra": { "Chip": "Snapdragon 8 Gen 2", "Screen": "6.73-inch LTPO AMOLED (120Hz)", "Camera": "Quad 50 MP + 50 MP + 50 MP + 50 MP (Leica)", "Battery": "5000 mAh", "Released": "2023" },
    "Xiaomi 14": { "Chip": "Snapdragon 8 Gen 3", "Screen": "6.36-inch LTPO AMOLED", "Camera": "Triple 50 MP + 50 MP + 50 MP", "Battery": "4610 mAh", "Released": "2023" },
    "Xiaomi 14 Pro": { "Chip": "Snapdragon 8 Gen 3", "Screen": "6.73-inch LTPO AMOLED", "Camera": "Triple 50 MP + 50 MP + 50 MP", "Battery": "4880 mAh", "Released": "2023" },
    "Xiaomi 14 Ultra": { "Chip": "Snapdragon 8 Gen 3", "Screen": "6.73-inch LTPO AMOLED", "Camera": "Quad 50 MP + 50 MP + 50 MP + 50 MP", "Battery": "5000 mAh", "Released": "2024" },
    "Xiaomi 15": { "Chip": "Snapdragon 8 Elite", "Screen": "6.36-inch LTPO AMOLED", "Camera": "Triple 50 MP + 50 MP + 50 MP", "Battery": "5400 mAh", "Released": "2024" },
    "Xiaomi 15 Pro": { "Chip": "Snapdragon 8 Elite", "Screen": "6.73-inch LTPO AMOLED", "Camera": "Triple 50 MP + 50 MP + 50 MP", "Battery": "6100 mAh", "Released": "2024" },
    "Xiaomi 16 Ultra": { "Chip": "Snapdragon 8 Elite", "Screen": "6.78-inch LTPO AMOLED", "Camera": "Quad 50 MP + 50 MP + 50 MP + 50 MP", "Battery": "5400 mAh", "Released": "2026" }
  },
  "OPPO": {
    "A103 Smiley Face": { "Chip": "Proprietary", "Screen": "2.4-inch TFT", "Camera": "1.3 MP", "Battery": "850 mAh", "Released": "2008" },
    "U529": { "Chip": "Proprietary", "Screen": "3.2-inch TFT Flip", "Camera": "5 MP", "Battery": "1000 mAh", "Released": "2010" },
    "Finder": { "Chip": "Snapdragon S3", "Screen": "4.3-inch Super AMOLED Plus", "Camera": "8 MP", "Battery": "1500 mAh", "Released": "2012" },
    "N1": { "Chip": "Snapdragon 600", "Screen": "5.9-inch IPS LCD", "Camera": "13 MP Rotating", "Battery": "3610 mAh", "Released": "2013" },
    "Find 7": { "Chip": "Snapdragon 801", "Screen": "5.5-inch 1440p IPS LCD", "Camera": "13 MP", "Battery": "3000 mAh", "Released": "2014" },
    "R7": { "Chip": "Snapdragon 615", "Screen": "5.0-inch AMOLED", "Camera": "13 MP", "Battery": "2320 mAh", "Released": "2015" },
    "F1 Plus": { "Chip": "MediaTek Helio P10", "Screen": "5.5-inch AMOLED", "Camera": "13 MP Rear / 16 MP Front", "Battery": "2850 mAh", "Released": "2016" },
    "Find X": { "Chip": "Snapdragon 845", "Screen": "6.42-inch AMOLED Panoramic", "Camera": "Dual 16 MP + 20 MP Sliding", "Battery": "3730 mAh", "Released": "2018" },
    "Reno 10x Zoom": { "Chip": "Snapdragon 855", "Screen": "6.6-inch AMOLED", "Camera": "Triple 48 MP + 13 MP + 8 MP (10x Hybrid)", "Battery": "4065 mAh", "Released": "2019" },
    "Find X2": { "Chip": "Snapdragon 865", "Screen": "6.7-inch AMOLED", "Camera": "Triple 48 MP + 13 MP + 12 MP", "Battery": "4200 mAh", "Released": "2020" },
    "Find X2 Pro": { "Chip": "Snapdragon 865", "Screen": "6.7-inch AMOLED (120Hz)", "Camera": "Triple 48 MP + 48 MP + 13 MP", "Battery": "4260 mAh", "Released": "2020" },
    "Find X3": { "Chip": "Snapdragon 870", "Screen": "6.7-inch LTPO AMOLED", "Camera": "Quad 50 MP + 50 MP + 13 MP + 3 MP", "Battery": "4500 mAh", "Released": "2021" },
    "Find X3 Pro": { "Chip": "Snapdragon 888", "Screen": "6.7-inch LTPO AMOLED", "Camera": "Quad 50 MP + 50 MP + 13 MP + 3 MP Microlens", "Battery": "4500 mAh", "Released": "2021" },
    "Find X5": { "Chip": "Snapdragon 888", "Screen": "6.55-inch AMOLED", "Camera": "Triple 50 MP + 13 MP + 50 MP", "Battery": "4800 mAh", "Released": "2022" },
    "Find X5 Pro": { "Chip": "Snapdragon 8 Gen 1", "Screen": "6.7-inch LTPO2 AMOLED", "Camera": "Triple 50 MP + 13 MP + 50 MP", "Battery": "5000 mAh", "Released": "2022" },
    "Find X6": { "Chip": "Dimensity 9200", "Screen": "6.74-inch AMOLED", "Camera": "Triple 50 MP + 50 MP + 50 MP", "Battery": "4800 mAh", "Released": "2023" },
    "Find X6 Pro": { "Chip": "Snapdragon 8 Gen 2", "Screen": "6.82-inch LTPO3 AMOLED", "Camera": "Triple 50 MP + 50 MP + 50 MP", "Battery": "5000 mAh", "Released": "2023" },
    "Find X7": { "Chip": "Dimensity 9300", "Screen": "6.78-inch AMOLED", "Camera": "Triple 50 MP + 64 MP + 50 MP", "Battery": "5000 mAh", "Released": "2024" },
    "Find X7 Ultra": { "Chip": "Snapdragon 8 Gen 3", "Screen": "6.82-inch LTPO AMOLED", "Camera": "Quad 50 MP + 50 MP + 50 MP + 50 MP (Dual Periscope)", "Battery": "5000 mAh", "Released": "2024" },
    "Find X8": { "Chip": "Dimensity 9400", "Screen": "6.59-inch LTPO AMOLED", "Camera": "Triple 50 MP + 50 MP + 50 MP", "Battery": "5630 mAh", "Released": "2024" },
    "Find X8 Pro": { "Chip": "Dimensity 9400", "Screen": "6.78-inch LTPO AMOLED", "Camera": "Quad 50 MP + 50 MP + 50 MP + 50 MP", "Battery": "5910 mAh", "Released": "2024" },
    "Find X8 Ultra": { "Chip": "MediaTek Dimensity 9400", "Screen": "6.82-inch LTPO AMOLED", "Camera": "Quad 50 MP + 50 MP + 50 MP + 50 MP", "Battery": "5910 mAh", "Released": "2025" }
  },
  "VIVO": {
    "X1": { "Chip": "MediaTek MT6577T", "Screen": "4.7-inch IPS LCD", "Camera": "8 MP", "Battery": "2000 mAh", "Released": "2012" },
    "Xplay 3S": { "Chip": "Snapdragon 801", "Screen": "6.0-inch 1440p IPS LCD", "Camera": "13 MP", "Battery": "3200 mAh", "Released": "2013" },
    "X5Max": { "Chip": "Snapdragon 615", "Screen": "5.5-inch Super AMOLED (4.75mm thin)", "Camera": "13 MP", "Battery": "2300 mAh", "Released": "2014" },
    "V3 Max": { "Chip": "Snapdragon 652", "Screen": "5.5-inch IPS LCD", "Camera": "13 MP", "Battery": "3000 mAh", "Released": "2016" },
    "X20 Plus UD": { "Chip": "Snapdragon 660", "Screen": "6.43-inch Super AMOLED (First In-Display Fingerprint)", "Camera": "Dual 12 MP + 5 MP", "Battery": "3900 mAh", "Released": "2018" },
    "NEX S": { "Chip": "Snapdragon 845", "Screen": "6.59-inch Super AMOLED Popup", "Camera": "Dual 12 MP + 5 MP", "Battery": "4000 mAh", "Released": "2018" },
    "V15 Pro": { "Shift": "Snapdragon 675", "Screen": "6.39-inch Super AMOLED Pop-up", "Camera": "Triple 48 MP + 8 MP + 5 MP", "Battery": "3700 mAh", "Released": "2019" },
    "X50 Pro+": { "Chip": "Snapdragon 865", "Screen": "6.56-inch AMOLED (120Hz Gymbal Stabilization)", "Camera": "Quad 50 MP + 13 MP + 32 MP + 13 MP", "Battery": "4350 mAh", "Released": "2020" },
    "X60": { "Chip": "Exynos 1080 / Snapdragon 870", "Screen": "6.56-inch AMOLED", "Camera": "Triple 48 MP + 13 MP + 13 MP", "Battery": "4300 mAh", "Released": "2021" },
    "X60 Pro": { "Chip": "Exynos 1080 / Snapdragon 870", "Screen": "6.56-inch AMOLED", "Camera": "Quad 48 MP + 13 MP + 13 MP + 8 MP", "Battery": "4200 mAh", "Released": "2021" },
    "X60 Pro+": { "Chip": "Snapdragon 888", "Screen": "6.56-inch AMOLED", "Camera": "Quad 50 MP + 8 MP + 32 MP + 48 MP", "Battery": "4200 mAh", "Released": "2021" },
    "X70": { "Chip": "Dimensity 1200", "Screen": "6.56-inch AMOLED", "Camera": "Triple 40 MP + 12 MP + 12 MP", "Battery": "4400 mAh", "Released": "2021" },
    "X70 Pro": { "Chip": "Exynos 1080 / Dimensity 1200", "Screen": "6.56-inch AMOLED", "Camera": "Quad 50 MP + 8 MP + 12 MP + 12 MP", "Battery": "4450 mAh", "Released": "2021" },
    "X70 Pro+": { "Chip": "Snapdragon 888+", "Screen": "6.78-inch LTPO AMOLED", "Camera": "Quad 50 MP + 8 MP + 12 MP + 48 MP", "Battery": "4500 mAh", "Released": "2021" },
    "X80": { "Chip": "Dimensity 9000", "Screen": "6.78-inch AMOLED", "Camera": "Triple 50 MP + 12 MP + 12 MP", "Battery": "4500 mAh", "Released": "2022" },
    "X80 Pro": { "Chip": "Snapdragon 8 Gen 1 / Dimensity 9000", "Screen": "6.78-inch LTPO3 AMOLED", "Camera": "Quad 50 MP + 8 MP + 12 MP + 48 MP (Zeiss)", "Battery": "4700 mAh", "Released": "2022" },
    "X90": { "Chip": "Dimensity 9200", "Screen": "6.78-inch AMOLED", "Camera": "Triple 50 MP + 12 MP + 12 MP", "Battery": "4810 mAh", "Released": "2022" },
    "X90 Pro": { "Chip": "Dimensity 9200", "Screen": "6.78-inch AMOLED", "Camera": "Triple 50.3 MP + 50 MP + 12 MP", "Battery": "4870 mAh", "Released": "2022" },
    "X90 Pro+": { "Chip": "Snapdragon 8 Gen 2", "Screen": "6.78-inch LTPO4 AMOLED", "Camera": "Quad 50.3 MP + 64 MP + 50 MP + 48 MP (1-inch Sensor)", "Battery": "4700 mAh", "Released": "2022" },
    "X100": { "Chip": "Dimensity 9300", "Screen": "6.78-inch LTPO AMOLED", "Camera": "Triple 50 MP + 64 MP + 50 MP", "Battery": "5000 mAh", "Released": "2023" },
    "X100 Pro": { "Chip": "Dimensity 9300", "Screen": "6.78-inch LTPO AMOLED", "Camera": "Triple 50 MP + 50 MP + 50 MP", "Battery": "5400 mAh", "Released": "2023" },
    "X100 Ultra": { "Chip": "Snapdragon 8 Gen 3", "Screen": "6.78-inch LTPO AMOLED", "Camera": "Triple 50 MP + 200 MP Periscope + 50 MP", "Battery": "5500 mAh", "Released": "2024" },
    "X200": { "Chip": "Dimensity 9400", "Screen": "6.67-inch LTPO AMOLED", "Camera": "Triple 50 MP + 50 MP + 50 MP", "Battery": "5800 mAh", "Released": "2024" },
    "X200 Pro": { "Chip": "MediaTek Dimensity 9400", "Screen": "6.78-inch LTPO AMOLED", "Camera": "Triple 50 MP + 200 MP Periscope + 50 MP", "Battery": "6000 mAh", "Released": "2025" }
  },
  "Infinix": {
    "Alpha X570": { "Chip": "MediaTek MT6589", "Screen": "5.7-inch IPS LCD", "Camera": "12 MP", "Battery": "2600 mAh", "Released": "2013" },
    "Hot X507": { "Chip": "MediaTek MT6582", "Screen": "5.0-inch IPS LCD", "Camera": "5 MP", "Battery": "2000 mAh", "Released": "2014" },
    "Zero 3": { "Chip": "MediaTek Helio X10", "Screen": "5.5-inch IPS LCD", "Camera": "20.7 MP", "Battery": "3030 mAh", "Released": "2015" },
    "Note 3 Pro": { "Chip": "MediaTek MT6753", "Screen": "6.0-inch IPS LCD", "Camera": "13 MP", "Battery": "4500 mAh", "Released": "2016" },
    "Zero 5": { "Chip": "MediaTek Helio P25", "Screen": "5.98-inch IPS LCD", "Camera": "Dual 12 MP + 13 MP", "Battery": "4350 mAh", "Released": "2017" },
    "Zero 6": { "Chip": "Snapdragon 636", "Screen": "6.18-inch IPS LCD", "Camera": "Dual 12 MP + 24 MP", "Battery": "3650 mAh", "Released": "2019" },
    "Zero 6 Pro": { "Chip": "Snapdragon 636", "Screen": "6.18-inch IPS LCD", "Camera": "Dual 12 MP + 24 MP", "Battery": "3650 mAh", "Released": "2019" },
    "S5": { "Chip": "MediaTek Helio P22", "Screen": "6.6-inch IPS LCD Punch-hole", "Camera": "Quad 16 MP + 5 MP + 2 MP + Low Light", "Battery": "4000 mAh", "Released": "2019" },
    "Note 7": { "Chip": "MediaTek Helio G70", "Screen": "6.95-inch IPS LCD", "Camera": "Quad 48 MP + 2 MP + 2 MP + 2 MP", "Battery": "5000 mAh", "Released": "2020" },
    "Zero 8": { "Chip": "MediaTek Helio G90T", "Screen": "6.85-inch IPS LCD (90Hz)", "Camera": "Quad 64 MP + 8 MP + 2 MP + 2 MP", "Battery": "4500 mAh", "Released": "2020" },
    "Zero X": { "Chip": "MediaTek Helio G95", "Screen": "6.67-inch AMOLED", "Camera": "Triple 64 MP + 8 MP + 8 MP", "Battery": "4500 mAh", "Released": "2021" },
    "Zero X Pro": { "Chip": "MediaTek Helio G95", "Screen": "6.67-inch AMOLED (120Hz)", "Camera": "Triple 108 MP + 8 MP + 8 MP", "Battery": "4500 mAh", "Released": "2021" },
    "Note 12 VIP": { "Chip": "MediaTek Helio G96", "Screen": "6.7-inch AMOLED (120Hz)", "Camera": "Triple 108 MP + 13 MP + 2 MP", "Battery": "4500 mAh (120W Charge)", "Released": "2022" },
    "Zero 20": { "Chip": "MediaTek Helio G99", "Screen": "6.7-inch AMOLED", "Camera": "Triple 108 MP + 13 MP + 2 MP", "Battery": "4500 mAh", "Released": "2022" },
    "Zero Ultra": { "Chip": "MediaTek Dimensity 920", "Screen": "6.8-inch AMOLED Curve", "Camera": "Triple 200 MP + 13 MP + 2 MP", "Battery": "4500 mAh (180W Charge)", "Released": "2022" },
    "Zero 30": { "Chip": "MediaTek Helio G99 / Dimensity 8020", "Screen": "6.78-inch AMOLED", "Camera": "Triple 108 MP + 2 MP + 2 MP", "Battery": "5000 mAh", "Released": "2023" },
    "GT 10 Pro": { "Chip": "MediaTek Dimensity 8050", "Screen": "6.67-inch AMOLED (120Hz)", "Camera": "Triple 108 MP + 2 MP + 2 MP", "Battery": "5000 mAh", "Released": "2023" },
    "Zero 40": { "Chip": "Dimensity 8200 Ultimate", "Screen": "6.78-inch AMOLED", "Camera": "Triple 108 MP + 50 MP + 2 MP", "Battery": "5000 mAh", "Released": "2024" },
    "GT 20 Pro": { "Chip": "MediaTek Dimensity 8200 Ultimate", "Screen": "6.78-inch AMOLED (144Hz)", "Camera": "Triple 108 MP + 2 MP + 2 MP", "Battery": "5000 mAh", "Released": "2024" },
    "Zero 5G 2026": { "Chip": "MediaTek Dimensity 7300", "Screen": "6.78-inch AMOLED", "Camera": "Triple 108 MP + 50 MP + 2 MP", "Battery": "5500 mAh", "Released": "2026" }
  },
  "Huawei": {
    "C300": { "Chip": "Proprietary", "Screen": "1.4-inch CSTN Color", "Camera": "None", "Battery": "600 mAh", "Released": "2004" },
    "U8150 Ideos": { "Chip": "Qualcomm MSM7225", "Screen": "2.8-inch TFT Touch", "Camera": "3.15 MP", "Battery": "1200 mAh", "Released": "2010" },
    "Ascend P1": { "Chip": "TI OMAP 4460 Dual", "Screen": "4.3-inch Super AMOLED", "Camera": "8.0 MP", "Battery": "1670 mAh", "Released": "2012" },
    "Ascend Mate": { "Chip": "Huawei K3V2 Quad", "Screen": "6.1-inch IPS LCD", "Camera": "8.0 MP", "Battery": "4050 mAh", "Released": "2013" },
    "Ascend P6": { "Chip": "Huawei K3V2", "Screen": "4.7-inch IPS+ LCD", "Camera": "8.0 MP", "Battery": "2000 mAh", "Released": "2013" },
    "Ascend Mate 7": { "Chip": "Kirin 925", "Screen": "6.0-inch IPS LCD Touch", "Camera": "13.0 MP", "Battery": "4100 mAh", "Released": "2014" },
    "P8": { "Chip": "Kirin 930 Octa", "Screen": "5.2-inch IPS-NEO", "Camera": "13.0 MP (OIS)", "Battery": "2680 mAh", "Released": "2015" },
    "P9": { "Chip": "Kirin 955", "Screen": "5.2-inch IPS LCD", "Camera": "Dual 12 MP (Leica Co-engineered)", "Battery": "3000 mAh", "Released": "2016" },
    "P9 Plus": { "Chip": "Kirin 955", "Screen": "5.5-inch IPS LCD", "Camera": "Dual 12 MP (Leica)", "Battery": "3400 mAh", "Released": "2016" },
    "Mate 9": { "Chip": "Kirin 960", "Screen": "5.9-inch IPS LCD", "Camera": "Dual 20 MP + 12 MP Leica", "Battery": "4000 mAh", "Released": "2016" },
    "P10": { "Chip": "Kirin 960", "Screen": "5.1-inch IPS LCD", "Camera": "Dual 20 MP + 12 MP", "Battery": "3200 mAh", "Released": "2017" },
    "P10 Plus": { "Chip": "Kirin 960", "Screen": "5.5-inch IPS LCD", "Camera": "Dual 20 MP + 12 MP Leica", "Battery": "3750 mAh", "Released": "2017" },
    "P20": { "Chip": "Kirin 970", "Screen": "5.8-inch LTPS IPS", "Camera": "Dual 12 MP + 20 MP", "Battery": "3400 mAh", "Released": "2018" },
    "P20 Pro": { "Chip": "Kirin 970 (NPU)", "Screen": "6.1-inch OLED", "Camera": "Triple 40 MP + 20 MP + 8 MP Leica", "Battery": "4000 mAh", "Released": "2018" },
    "Mate 20 Pro": { "Chip": "Kirin 980 (7nm)", "Screen": "6.39-inch OLED Curved", "Camera": "Triple 40 MP + 20 MP + 8 MP Leica", "Battery": "4200 mAh", "Released": "2018" },
    "P30": { "Chip": "Kirin 980", "Screen": "6.1-inch OLED", "Camera": "Triple 40 MP + 16 MP + 8 MP", "Battery": "3600 mAh", "Released": "2019" },
    "P30 Pro": { "Chip": "Kirin 980", "Screen": "6.47-inch OLED (5x Optical Periscope)", "Camera": "Quad 40 MP + 8 MP + 20 MP + TOF", "Battery": "4200 mAh", "Released": "2019" },
    "Mate 30 Pro": { "Chip": "Kirin 990 5G", "Screen": "6.53-inch Horizon Display OLED", "Camera": "Quad 40 MP + 40 MP + 8 MP + TOF", "Battery": "4500 mAh", "Released": "2019" },
    "P40": { "Chip": "Kirin 990 5G", "Screen": "6.1-inch OLED", "Camera": "Triple 50 MP + 8 MP + 16 MP", "Battery": "3800 mAh", "Released": "2020" },
    "P40 Pro": { "Chip": "Kirin 990 5G", "Screen": "6.58-inch OLED (90Hz Quad-curve)", "Camera": "Quad 50 MP + 12 MP + 40 MP + TOF", "Battery": "4200 mAh", "Released": "2020" },
    "P40 Pro+": { "Chip": "Kirin 990 5G", "Screen": "6.58-inch OLED (90Hz)", "Camera": "Penta 50 MP + 8 MP + 8 MP + 40 MP + TOF", "Battery": "4200 mAh", "Released": "2020" },
    "Mate 40 Pro": { "Chip": "Kirin 9000 (5nm)", "Screen": "6.76-inch OLED (90Hz)", "Camera": "Triple 50 MP + 12 MP + 20 MP Leica", "Battery": "4400 mAh", "Released": "2020" },
    "P50": { "Chip": "Snapdragon 888 4G", "Screen": "6.5-inch OLED (90Hz)", "Camera": "Triple 50 MP + 12 MP + 13 MP", "Battery": "4100 mAh", "Released": "2021" },
    "P50 Pro": { "Chip": "Snapdragon 888 / Kirin 9000", "Screen": "6.6-inch OLED (120Hz Dual-Matrix)", "Camera": "Quad 50 MP + 64 MP + 13 MP + 40 MP", "Battery": "4360 mAh", "Released": "2021" },
    "Mate 50 Pro": { "Chip": "Snapdragon 8+ Gen 1 4G", "Screen": "6.74-inch OLED (120Hz Physical Aperture)", "Camera": "Triple 50 MP + 64 MP + 13 MP", "Battery": "4700 mAh", "Released": "2022" },
    "P60": { "Chip": "Snapdragon 8+ Gen 1 4G", "Screen": "6.67-inch LTPO OLED", "Camera": "Triple 48 MP + 12 MP + 13 MP", "Battery": "4815 mAh", "Released": "2023" },
    "P60 Pro": { "Chip": "Snapdragon 8+ Gen 1 4G", "Screen": "6.67-inch LTPO OLED", "Camera": "Triple 48 MP + 48 MP + 13 MP", "Battery": "4815 mAh", "Released": "2023" },
    "Mate 60 Pro": { "Chip": "Kirin 9000S (5G return)", "Screen": "6.82-inch LTPO OLED", "Camera": "Triple 50 MP + 48 MP + 12 MP", "Battery": "5000 mAh", "Released": "2023" },
    "Pura 70": { "Chip": "Kirin 9010", "Screen": "6.6-inch LTPO OLED", "Camera": "Triple 50 MP + 12 MP + 13 MP", "Battery": "4900 mAh", "Released": "2024" },
    "Pura 70 Pro": { "Chip": "Kirin 9010", "Screen": "6.8-inch LTPO OLED", "Camera": "Triple 50 MP + 48 MP + 12.5 MP", "Battery": "5050 mAh", "Released": "2024" },
    "Pura 70 Ultra": { "Chip": "Kirin 9010", "Screen": "6.8-inch LTPO OLED", "Camera": "Triple 50 MP Retractable (1-inch) + 50 MP + 40 MP", "Battery": "5200 mAh", "Released": "2024" },
    "Mate XT Ultimate": { "Chip": "Kirin 9010", "Screen": "10.2-inch Tri-Foldable LTPO OLED", "Camera": "Triple 50 MP + 12 MP + 12 MP", "Battery": "5600 mAh", "Released": "2024" }
  }
}